[1,["40uekieHRPYqpCy82wJ8N0","f033cmmYpMeKk7mUIpJ85n@f9941","c151es9btG7bhq/av/eutV@f9941","2enlIIayRFJqncA01jOClL@6c48a","5b3Nl+NyJJaqX73kfGzq9n@6c48a","97m8KJF5RKIIxSzw4kOki/@f9941","d8vzbehkVN+Z9hfI4is0S3@f9941","c74Kqw8ixJDpa3u7bx3iOM@f9941","ffuIqPr2JI9I8dPLYGRDpD@f9941","5b3Nl+NyJJaqX73kfGzq9n@f9941","7bBUqwTn1LaYLgdyFnwEQm@f9941","2enlIIayRFJqncA01jOClL@f9941","afxHkx8GZGsJC+n+YfITQo@f9941","7bBUqwTn1LaYLgdyFnwEQm@6c48a","97m8KJF5RKIIxSzw4kOki/@6c48a","afxHkx8GZGsJC+n+YfITQo@6c48a","c151es9btG7bhq/av/eutV@6c48a","c74Kqw8ixJDpa3u7bx3iOM@6c48a","d8vzbehkVN+Z9hfI4is0S3@6c48a","f033cmmYpMeKk7mUIpJ85n@6c48a","ffuIqPr2JI9I8dPLYGRDpD@6c48a"],["node","_spriteFrame","_textureSource","_font","_parent","pointLabel","_target","_cameraComponent","tips","game","timeLabel","layout","input","win","_placeholderLabel","_textLabel","scene","_scrollView"],[["cc.Label",["_string","_actualFontSize","_fontSize","_id","_overflow","_isSystemFontUsed","_isBold","_lineHeight","_horizontalAlign","_enableWrapText","_verticalAlign","node","_font","_color"],-8,1,6,5],"cc.SpriteFrame",["cc.Node",["_name","_layer","_id","_active","_components","_parent","_children","_lpos"],-1,9,1,2,5],["cc.Node",["_name","_layer","_id","_active","_components","_parent","_lpos","_children"],-1,12,1,5,2],["cc.Widget",["_alignFlags","_id","_top","_left","_right","_originalWidth","_originalHeight","_alignMode","_bottom","node","_target"],-6,1,1],["cc.Sprite",["_id","_sizeMode","_type","node","_spriteFrame","_color"],0,1,6,5],["cc.UITransform",["_id","node","_contentSize","_anchorPoint"],2,1,5,5],["cc.LabelOutline",["_id","node","_color"],2,1,5],["cc.TTFFont",["_name","_native"],1],["cc.SceneAsset",["_name"],2],["cc.Node",["_name","_id","_parent","_components","_lpos"],1,1,2,5],["cc.Canvas",["_id","node","_cameraComponent"],2,1,1],["048eec0espDDLQkreoRD8P8",["_id","node","tips"],2,1,1],["53af0GNG7tLDqY+5I97P94a",["_id","node","game"],2,1,1],["ba648pSajtIoYID+pja5Fbs",["_id","node","win","input","tips","layout","pointLabel","timeLabel"],2,1,1,1,1,1,1,1],["cc.EditBox",["_inputMode","_maxLength","_id","node","_textLabel","_placeholderLabel"],0,1,1,1],["cc.UIOpacity",["_opacity","_id","node"],1,1],["cc.Button",["_transition","_zoomScale","_id","node","clickEvents","_target"],0,1,9,1],["cc.ClickEvent",["_componentId","handler","target"],1,1],["cc.Mask",["_id","node"],2,1],["cc.Graphics",["_id","node","_fillColor"],2,1,5],["cc.Scene",["_name","_id","_children","_globals"],1,2,4],["cc.SceneGlobals",["ambient","shadows","_skybox","fog","octree","skin","lightProbeInfo","postSettings"],3,4,4,4,4,4,4,4,4],["cc.AmbientInfo",["_skyColorHDR","_groundAlbedoHDR"],3,5,5],["cc.ShadowsInfo",["_shadowColor","_size"],3,5,5],["cc.SkyboxInfo",[],3],["cc.FogInfo",[],3],["cc.OctreeInfo",[],3],["cc.SkinInfo",["_enabled"],2],["cc.LightProbeInfo",[],3],["cc.PostSettingsInfo",[],3],["cc.Camera",["_projection","_orthoHeight","_near","_visibility","_id","node","_color"],-2,1,5],["cc.ScrollBar",["_direction","_id","node","_handle"],1,1,1],["cc.ScrollView",["bounceDuration","brake","horizontal","_id","node","_content","_verticalScrollBar"],-1,1,1,1],["cc.Layout",["_resizeMode","_layoutType","_spacingX","_id","node"],-1,1],["e1b4bc5lv1DJb2QEexma3q+",["_id","node"],2,1],["62153elj0VEGITabjos1C70",["_id","node"],2,1]],[[6,0,1,2,2],[2,0,1,2,5,4,7,4],[7,0,1,2],[5,1,0,3,4,3],[2,0,1,2,5,6,4,7,4],[6,0,1,2,3,2],[3,0,1,2,5,4,6,4],[3,0,1,2,5,7,4,6,4],[5,0,3,4,2],[16,0,1,2,3],[0,0,1,2,3,11,5],[2,0,1,2,5,6,4,4],[6,0,1,2],[17,0,1,2,3,4,5,4],[18,0,1,2,3],[8,0,1,3],[9,0,2],[2,0,1,2,6,4,7,4],[2,0,3,1,2,5,6,4,5],[2,0,3,1,2,4,7,5],[2,0,1,2,5,4,4],[3,0,3,1,2,5,7,4,5],[3,0,1,2,7,4,6,4],[3,0,1,2,5,4,4],[3,0,3,1,2,5,4,6,5],[10,0,1,2,3,4,3],[11,0,1,2,2],[4,0,2,1,9,4],[4,0,3,4,5,1,9,10,6],[4,0,3,2,1,9,10,5],[4,0,6,7,1,9,5],[4,0,3,8,1,9,5],[4,0,4,2,1,9,5],[12,0,1,2,2],[5,2,1,0,3,5,4],[5,2,1,0,3,4,4],[5,2,1,0,3,4],[13,0,1,2,2],[14,0,1,2,3,4,5,6,7,2],[15,0,1,2,3,4,5,4],[19,0,1,2],[20,0,1,2,2],[0,0,1,2,7,4,3,11,7],[0,0,1,2,4,3,11,6],[0,0,1,2,5,6,3,11,12,7],[0,0,1,2,4,5,6,3,11,13,12,8],[0,0,1,2,4,5,6,3,11,12,8],[0,0,8,10,1,2,7,4,5,3,11,12,10],[0,0,1,2,4,5,6,3,11,8],[0,0,1,2,3,11,13,5],[0,0,1,2,4,5,6,3,11,13,8],[0,0,8,1,2,4,9,3,11,8],[0,0,8,1,2,7,4,9,3,11,13,9],[7,0,1,2,2],[21,0,1,2,3,3],[22,0,1,2,3,4,5,6,7,1],[23,0,1,1],[24,0,1,1],[25,1],[26,1],[27,1],[28,0,2],[29,1],[30,1],[31,0,1,2,3,4,5,6,6],[32,0,1,2,3,3],[33,0,1,2,3,4,5,6,5],[34,0,1,2,3,4,5],[35,0,1,2],[36,0,1,2]],[[[{"name":"nhanvat","rect":{"x":2,"y":2,"width":362,"height":300},"offset":{"x":0,"y":0},"originalSize":{"width":366,"height":304},"rotated":false,"capInsets":[0,0,0,0],"vertices":{"rawPosition":[-181,-150,0,181,-150,0,-181,150,0,181,150,0],"indexes":[0,1,2,2,1,3],"uv":[2,302,364,302,2,2,364,2],"nuv":[0.00546448087431694,0.006578947368421052,0.994535519125683,0.006578947368421052,0.00546448087431694,0.993421052631579,0.994535519125683,0.993421052631579],"minPos":{"x":-181,"y":-150,"z":0},"maxPos":{"x":181,"y":150,"z":0}},"packable":true,"pixelsToUnit":100,"pivot":{"x":0.5,"y":0.5},"meshType":0}],[1],0,[0],[2],[3]],[[[15,"fontchinh","fontchinh.ttf"],-1],0,0,[],[],[]],[[{"name":"info","rect":{"x":0,"y":0,"width":445,"height":398},"offset":{"x":-1.5,"y":1.5},"originalSize":{"width":448,"height":401},"rotated":false,"capInsets":[0,0,0,0],"vertices":{"rawPosition":[-222.5,-199,0,222.5,-199,0,-222.5,199,0,222.5,199,0],"indexes":[0,1,2,2,1,3],"uv":[0,401,445,401,0,3,445,3],"nuv":[0,0.007481296758104738,0.9933035714285714,0.007481296758104738,0,1,0.9933035714285714,1],"minPos":{"x":-222.5,"y":-199,"z":0},"maxPos":{"x":222.5,"y":199,"z":0}},"packable":true,"pixelsToUnit":100,"pivot":{"x":0.5,"y":0.5},"meshType":0}],[1],0,[0],[2],[4]],[[[16,"game"],[17,"main",33554432,"beI88Z2HpFELqR4T5EMHpg",[-7,-8,-9,-10,-11,-12,-13],[[0,"d6rUX5yfhMlKoWX2bSbawx",-1,[5,450,819.9999999999999]],[26,"12O/ljcVlEqLmVm3U2gEOQ",-3,-2],[27,45,1.1368683772161603e-13,"c5V1EV8IpMtrIvY1OE9t2u",-4],[33,"d10DYcrYFGa4qkK7cqnmHK",-6,-5]],[1,225,409.99999999999994,0]],[11,"Box",33554432,"956MxejYpEp7i+z/Uc9Ncn",1,[-19,-20,-21],[[0,"b6ClVlH3JNzKNK80op/yfv",-14,[5,387.379,372.071]],[3,0,"85udo7iktA7KJm6WCo4tjM",-15,6],[28,42,31.31049999999999,31.31049999999999,387.379,"b2ToSnJ8hOQo/DxwIreyE/",-16,1],[37,"c3zzuaMQdKNpoenx4gREe9",-18,-17]]],[21,"win",false,33554432,"bf3TE6R8dNh6szLOMrYSSF",1,[-25,-26,-27,-28,-29],[[[0,"3ef0IuoIZBLIhrMtwgPPb7",-22,[5,362,300]],[8,"57hmsT1pFOr6wyU6lngz01",-23,15],-24],4,4,1]],[18,"game",false,33554432,"b9SjqvSr9If4KM9f6ctqcw",1,[-37,-38,-39,-40],[[12,"b0MBIGAydJ9ImXuIyR2EMP",-30],[38,"bcdJ1q/oRGn6W6Z4NroqpR",-36,-35,-34,2,-33,-32,-31]]],[7,"EditBox",33554432,"19hjcZC1hHw5aF4udh4xpx",1,[-48,-49],[[[0,"f3LuoV+w9G2YMu3XMwP6lh",-41,[5,1,1]],[34,1,0,"672O+1WZdAJ5kIAba0fMcl",-42,[4,301989887]],[39,6,800,"cemYzkhjRGdJQP/fVU4sX2",-45,-44,-43],-46,[9,0,"b2Q2i1SdJJ5qygLYsJGm64",-47]],4,4,4,1,4],[1,60.08649999999999,-399.284,0]],[7,"life",33554432,"973UPV4itJdafvhNBkt/Y7",4,[-53,-54,-55],[[[0,"31mKXULXtDyaVOXFg0xmLH",-50,[5,88,100]],-51,[29,9,8.687999999999988,26.98899999999992,"a49Dvj0wBBcKQpVOQPbuuM",-52,1]],4,1,4],[1,-172.312,333.011,0]],[22,"scrollBar",33554432,"3bsiU6TG1MSJ0IW2GxH6jH",[-60],[[[5,"18gFiYKVZEY6QlNrn/hmwt",-56,[5,12,327.058],[0,1,0.5]],[35,1,0,"98AaAphDhGNZsTqA5qmHVV",-57,3],[30,37,250,1,"e6bD+iY/pLZI9ZpmKMxfIz",-58],-59],4,4,4,1],[1,188.279,0,0]],[4,"button",33554432,"ca8ss0lVBJNYBpGvupHEBF",2,[-65],[[0,"90trAbWyFKpLjaOds95L5W",-61,[5,157.44,65.278]],[3,0,"03lzIpp8pM/pXqe9HCY7D/",-62,5],[13,3,1.5,"37rNjYFPJCJJyxZhwC12Fa",-64,[[14,"53af0GNG7tLDqY+5I97P94a","player",2]],-63]],[1,-8.350999999999999,-193.59599999999995,0]],[4,"button",33554432,"24C1kc3hpDMrTm+Rby9L5u",3,[-70],[[0,"cehfY831REpaKRWAp+PlPh",-66,[5,157.44,65.278]],[3,0,"66I/afy1VD66GXSZW7BbAr",-67,14],[13,3,1.5,"22XeQ+totEGJ3d42mVwOot",-69,[[14,"53af0GNG7tLDqY+5I97P94a","player",2]],-68]],[1,-4.556000000000012,-158.17699999999994,0]],[7,"content",33554432,"41nJBC3Q9AMK/Wo0w48Jk4",2,[7,-73],[[[0,"65Ful2cFND3aaPG71IbXQu",-71,[5,376.558,327.058]],-72],4,1],[1,0,-14.144,0]],[4,"view",33554432,"5egviy9g1Ca5obpZNaXzrl",10,[-77],[[0,"152Y+jC25Jw4PMeQHeO4dR",-74,[5,359.977,323.644]],[40,"fcOTW/66BER760hZEd+QpM",-75],[41,"a90imJ/CBP65PXqQypECgm",-76,[4,16777215]]],[1,-7.3155,1.7070000000000007,0]],[4,"time",33554432,"48/TFBhLxN54G2clYTtiuQ",4,[-81],[[0,"3auzBzw71KSIPpY9hBepra",-78,[5,344,33]],[8,"49R8Nm5BpPkrqoeNMeyj3F",-79,10],[31,12,-158.34,-344.435,"a6rTjAAmJCp543IZZNg08n",-80]],[1,-36.34,-377.935,0]],[1,"vietnam",33554432,"b6GZzN8YhOaoS8wgCeoWFj",1,[[0,"85kM6pYQ9PjY/jmJCooQG2",-82,[5,92.741,59.224]],[3,0,"522PbCJFdPUal+tSpMzRJJ",-83,1],[32,33,6.853500000000011,36.83099999999983,"6c4UdEOIlI5IdcNz3vHk+g",-84]],[1,171.776,343.5570000000001,0]],[4,"title",33554432,"cfsypRUtlCSqtaCPuz3WpR",2,[-87],[[0,"8eSwa2pKlPYYzx7/Gq4SY1",-85,[5,374,58]],[8,"8ecXcQXXxNiZur0zsaRly4",-86,2]],[1,5.7620000000000005,182.94600000000003,0]],[1,"text",33554432,"8fBkcMOtFMc6A+q1J2a7w1",14,[[0,"83LLg9nxlCo4Fnh8PRZFkA",-88,[5,213.98085937500002,29.2]],[42,"Hướng dẫn tân thủ",20,20,20,3,"f7BdPcLhVInaXYJ/s5CmJp",-89],[2,"7frf301WlEpYMk46dJBHrd",-90]],[1,-5.7620000000000005,-7.264999999999986,0]],[4,"content",33554432,"c04TNw0yZHz6E/6qcetZbh",11,[-92],[[5,"74j3xsulJL3pPbQ7TK4wLr",-91,[5,357.39099999999996,362.77700000000004],[0,0.5,1]]],[1,0.170499999999997,161.09,0]],[1,"Label",33554432,"c5rRK+fy1Kx4g7HEnN6FRs",8,[[0,"2cJF8XNQ9GkalVxS6/0WgV",-93,[5,96.05078125,54.4]],[10,"Chơi ngay",20,20,"575wQOF2FG/7K27D96R1fj",-94],[2,"a94jvT8KBKUJEjuaI+jhA+",-95]],[1,2.641999999999996,5.944000000000017,0]],[6,"Label",33554432,"41jCmc1BdFqbVTWDSh5KRu",12,[[[0,"e8aZ57u1VA5L+tEChs48q/",-96,[5,167.108859375,54.4]],-97,[53,"50LrPiTrdC/qrbMEseK9jJ",-98,[4,4278190335]]],4,1,4],[1,55.161500000000004,1.981,0]],[4,"Label",33554432,"26xFlUoPNNjLPAZkBeXGYd",4,[-101],[[0,"b5lElZf8ZDPaG1z+RBgxea",-99,[5,52.2265625,50.4]],[10,"Điểm:",20,20,"668W6vsbtK8JdoPCzt/atb",-100]],[1,113.956,381.097,0]],[6,"point",33554432,"8daqqmdAdGH65ucXI32gPZ",19,[[[0,"7dKwNr1rxAJ7WZjX9fqWkn",-102,[5,48.4921875,54.4]],-103,[2,"c02d+sNwBN25aeBK4IKSw1",-104]],4,1,4],[1,67.252,0,0]],[19,"demo",false,33554432,"37bUtCXLRKE4qbhC5G4h2q",[[0,"25Cf4eKthM3bMnsDCg6wlV",-105,[5,56.2265625,54.4]],[43,"int04",20,20,3,"2cP1xJIAVKtZUm8Qw0dSer",-106],[2,"cc8o52vdNITbwcYg0/a1Aa",-107]],[1,-12.875,355.8970000000001,0]],[1,"Label",33554432,"3dak4Mr+BNP6ZDsyZVOxM2",3,[[0,"9fHkQinYJAz6F82AZmjpvF",-108,[5,82.99993896484375,54.4]],[44,"TỔNG KẾT",20,20,false,true,"ecc0fHhp5ID6Lqh7X0EPgs",-109,11],[2,"3c17stHjxLYqNFQG8A34RO",-110]],[1,0,127.625,0]],[23,"POINT",33554432,"daDM9GyuZIVKDOqkUDHNA7",3,[[[0,"6fSt3OXYNAk6h68Z8/ULWO",-111,[5,122.49993896484375,54.4]],-112,[2,"f6ka1D4EVF143UJTKh6nEX",-113]],4,1,4]],[1,"POINT-001",33554432,"39oEDJWD9I2JYnEb0y9NPA",3,[[0,"98TQ2zBVpK65QGzJ+aPjM7",-114,[5,191.02293896484375,54.4]],[45,"Điểm số của bạn:",29,30,2,false,true,"35gkFK9DVB6rOpUkn5ETi8",-115,[4,3623939071],12],[2,"cbcrHfpZ9Jdq32fBOXW9JS",-116]],[1,0,53.96300000000008,0]],[1,"Label-001",33554432,"cadPEt2D5CRYIVVQB4T1LV",3,[[0,"e3k7bO1RBFD4Qjve/Xne25",-117,[5,309.98293896484375,94.39999999999999]],[46,"Tích cực cào phím để cuộc sống trở nên đẹp hơn nhé coder =)))",20,20,3,false,true,"2cRCyK4tdJoJ6Uxc7J56Pv",-118,13],[2,"0fawaCxwtBApjNwQ1KL4lu",-119]],[1,0,-74.39999999999992,0]],[1,"Label",33554432,"dctusPnmlKEJafMZ/FhwN0",9,[[0,"848n18gKJKAYPbXidffCmG",-120,[5,72.69140625,54.4]],[10,"Chơi lại",20,20,"f7bhpW4CFD1Lz7JiuUPspx",-121],[2,"88Ipzrb6FNd5pV1Un0U2mS",-122]],[1,2.641999999999996,5.944000000000017,0]],[24,"TEXT_LABEL",false,33554432,"5cKVWtrqBFcLslCEdbMRh2",5,[[[5,"72hJSi6SJAOY5KTwIAThF9",-123,[5,-1,1],[0,0,1]],-124,[9,0,"ac7fms78RDZq5oGTPBmCYZ",-125]],4,1,4],[1,1.5,0.5,0]],[6,"PLACEHOLDER_LABEL",33554432,"4cYiXbOtJMH47WpZZQqTj3",5,[[[5,"50uqQ9F2NH8JoWznowZqkX",-126,[5,-1,1],[0,0,1]],-127,[9,0,"9fXab/ExFIYLcRbzBes+KM",-128]],4,1,4],[1,1.5,0.5,0]],[20,"background",33554432,"188Vy8W6xJl7Sv41yzPcqH",1,[[0,"02Y5JOyZtKbILlSAyq0F6U",-129,[5,451.93499999999995,819.365]],[3,0,"faCqCt3+pJ0p9jiB4PZLzc",-130,0]]],[6,"bar",33554432,"a3BrI28cpAvqwrS86RypSs",7,[[[5,"24PhBL7ohAOYiDp0kmDeAp",-131,[5,10,156.25],[0,0,0]],-132],4,1],[1,-9.048999999999978,5.816000000000031,0]],[1,"item",33554432,"4faKv5lTVJZIi2/paAem5r",16,[[5,"9dHdEbE69OY6Phdl0Yf/DU",-133,[5,343.49012500000003,306.5],[0,0,1]],[47,"Chào mừng bạn đến với trò chơi nhập chữ.\nBấm nút chơi để chơi,  bạn có 3 mạng.\nNhiệm vụ của bạn cần gõ các phím để hoàn tất.\nNếu bạn để chữ rơi xuống khỏi màn hình, bạn sẽ bị mất một mạng.\nChúc bạn may mắn.\n\nTrò chơi được viết bởi: \n- @int04\n- Github: @int04\n- engine: cococ creator.",0,0,20,20,25,3,false,"94LFhb9GhMj6khQFVxAL6p",-134,4]],[1,-176.423,-10.149999999999977,0]],[1,"1",33554432,"48jeG1ggdFia+DkXClKl2I",6,[[0,"96ADNicLJHoZM0dv0RpiCs",-135,[5,26,23]],[3,0,"65WloQHaRDlobCrVjWXB88",-136,7]],[1,-31,55.659,0]],[1,"2",33554432,"c67AvsP4xB6Zx9IpxiZUaW",6,[[0,"b7OC9enABHGJw1f3hZ1J0I",-137,[5,26,23]],[3,0,"27AiDgYEdCS4UiF5B1TCvL",-138,8]],[1,0,55.659,0]],[1,"3",33554432,"47SkwRrU9EIoopR5L6JCS0",6,[[0,"5dtDBzhHNLRIpbSc0rZPBS",-139,[5,26,23]],[3,0,"3ejuV2mzNGmLgplqWYg2Nn",-140,9]],[1,31,55.659,0]],[11,"string",33554432,"ef9MgIzoxBVbFiHnNuVkwp",4,[21],[[12,"d3Rcdys9dEGr+3riZNoc6s",-141]]],[54,"game","6bcb978a-1b6a-47b3-a1b5-8585635f5f39",[1],[55,[56,[2,0,0,0,0.520833125],[2,0,0,0,0]],[57,[4,4283190348],[0,512,512]],[58],[59],[60],[61,false],[62],[63]]],[25,"Camera","ebFwiq8gBFaYpqYbdoDODe",1,[-142],[1,0,0,1000]],[64,0,410,0,1108344832,"63WIch3o5BEYRlXzTT0oWc",37,[4,4278190080]],[36,1,0,"79gPrD8dBEVaU+nCm3NYc/",30],[65,1,"cbVdMBnbFGv5XSGPHHKYk2",7,39],[66,0.23,0.75,false,"00xO7GIr1CdYILRfksZXJl",10,16,40],[67,1,1,5,"eaDZhHj5RAaZs7UGXIOHe0",6],[48,"100",20,20,3,false,true,"5fhZzHY9hEQ6RypkJhCiNv",18],[49,"9999",20,20,"8aTT63CZJE1q/0ZpDChV/I",20,[4,4279769343]],[68,"f9s0OwrnhKHr/FLk9yb7zX",3],[50,"9999999",31,30,2,false,true,"905uJDgFhLioYpN5D7gsRx",23,[4,4282908416]],[69,"024uxiS6FB2b7lcUs3jelQ",5],[51,"",0,40,20,1,false,"der9bjjoxHe7sya5mVp23q",27],[52,"Enter text here...",0,20,20,1,1,false,"8cCDjpjp9Br70uruKzoWju",28,[4,4290493371]]],0,[0,0,1,0,7,38,0,0,1,0,0,1,0,8,2,0,0,1,0,-1,37,0,-2,29,0,-3,13,0,-4,2,0,-5,4,0,-6,3,0,-7,5,0,0,2,0,0,2,0,0,2,0,9,4,0,0,2,0,-1,14,0,-2,10,0,-3,8,0,0,3,0,0,3,0,-3,45,0,-1,22,0,-2,23,0,-3,24,0,-4,25,0,-5,9,0,0,4,0,10,43,0,5,44,0,11,42,0,12,47,0,13,45,0,0,4,0,-1,6,0,-2,12,0,-3,19,0,-4,35,0,0,5,0,0,5,0,14,49,0,15,48,0,0,5,0,-4,47,0,0,5,0,-1,27,0,-2,28,0,0,6,0,-2,42,0,0,6,0,-1,32,0,-2,33,0,-3,34,0,0,7,0,0,7,0,0,7,0,-4,40,0,-1,30,0,0,8,0,0,8,0,6,8,0,0,8,0,-1,17,0,0,9,0,0,9,0,6,9,0,0,9,0,-1,26,0,0,10,0,-2,41,0,-2,11,0,0,11,0,0,11,0,0,11,0,-1,16,0,0,12,0,0,12,0,0,12,0,-1,18,0,0,13,0,0,13,0,0,13,0,0,14,0,0,14,0,-1,15,0,0,15,0,0,15,0,0,15,0,0,16,0,-1,31,0,0,17,0,0,17,0,0,17,0,0,18,0,-2,43,0,0,18,0,0,19,0,0,19,0,-1,20,0,0,20,0,-2,44,0,0,20,0,0,21,0,0,21,0,0,21,0,0,22,0,0,22,0,0,22,0,0,23,0,-2,46,0,0,23,0,0,24,0,0,24,0,0,24,0,0,25,0,0,25,0,0,25,0,0,26,0,0,26,0,0,26,0,0,27,0,-2,48,0,0,27,0,0,28,0,-2,49,0,0,28,0,0,29,0,0,29,0,0,30,0,-2,39,0,0,31,0,0,31,0,0,32,0,0,32,0,0,33,0,0,33,0,0,34,0,0,34,0,0,35,0,-1,38,0,16,36,1,4,36,7,4,10,21,4,35,40,17,41,45,5,46,142],[0,0,0,0,0,0,0,0,0,0,0,0,0,0,0,0,39,43,46],[1,1,1,1,3,1,1,1,1,1,1,3,3,3,1,1,1,3,3],[5,6,7,8,0,2,9,1,1,1,10,0,0,0,2,11,12,0,0]],[[{"name":"time","rect":{"x":1,"y":3,"width":344,"height":33},"offset":{"x":-2.5,"y":-1.5},"originalSize":{"width":351,"height":36},"rotated":false,"capInsets":[0,0,0,0],"vertices":{"rawPosition":[-172,-16.5,0,172,-16.5,0,-172,16.5,0,172,16.5,0],"indexes":[0,1,2,2,1,3],"uv":[1,33,345,33,1,0,345,0],"nuv":[0.002849002849002849,0,0.9829059829059829,0,0.002849002849002849,0.9166666666666666,0.9829059829059829,0.9166666666666666],"minPos":{"x":-172,"y":-16.5,"z":0},"maxPos":{"x":172,"y":16.5,"z":0}},"packable":true,"pixelsToUnit":100,"pivot":{"x":0.5,"y":0.5},"meshType":0}],[1],0,[0],[2],[13]],[[{"name":"background-x","rect":{"x":0,"y":0,"width":356,"height":605},"offset":{"x":0,"y":0},"originalSize":{"width":356,"height":605},"rotated":false,"capInsets":[0,0,0,0],"vertices":{"rawPosition":[-178,-302.5,0,178,-302.5,0,-178,302.5,0,178,302.5,0],"indexes":[0,1,2,2,1,3],"uv":[0,605,356,605,0,0,356,0],"nuv":[0,0,1,0,0,1,1,1],"minPos":{"x":-178,"y":-302.5,"z":0},"maxPos":{"x":178,"y":302.5,"z":0}},"packable":true,"pixelsToUnit":100,"pivot":{"x":0.5,"y":0.5},"meshType":0}],[1],0,[0],[2],[14]],[[{"name":"default_scrollbar_vertical","rect":{"x":0,"y":0,"width":15,"height":30},"offset":{"x":0,"y":0},"originalSize":{"width":15,"height":30},"rotated":false,"capInsets":[4,10,4,10],"vertices":{"rawPosition":[-7.5,-15,0,7.5,-15,0,-7.5,15,0,7.5,15,0],"indexes":[0,1,2,2,1,3],"uv":[0,30,15,30,0,0,15,0],"nuv":[0,0,1,0,0,1,1,1],"minPos":{"x":-7.5,"y":-15,"z":0},"maxPos":{"x":7.5,"y":15,"z":0}},"packable":true,"pixelsToUnit":100,"pivot":{"x":0.5,"y":0.5},"meshType":0}],[1],0,[0],[2],[15]],[[{"name":"button_orange","rect":{"x":0,"y":0,"width":240,"height":95},"offset":{"x":0,"y":0},"originalSize":{"width":240,"height":95},"rotated":false,"capInsets":[0,0,0,0],"vertices":{"rawPosition":[-120,-47.5,0,120,-47.5,0,-120,47.5,0,120,47.5,0],"indexes":[0,1,2,2,1,3],"uv":[0,95,240,95,0,0,240,0],"nuv":[0,0,1,0,0,1,1,1],"minPos":{"x":-120,"y":-47.5,"z":0},"maxPos":{"x":120,"y":47.5,"z":0}},"packable":true,"pixelsToUnit":100,"pivot":{"x":0.5,"y":0.5},"meshType":0}],[1],0,[0],[2],[16]],[[{"name":"title","rect":{"x":0,"y":0,"width":374,"height":58},"offset":{"x":0,"y":0},"originalSize":{"width":374,"height":58},"rotated":false,"capInsets":[0,0,0,0],"vertices":{"rawPosition":[-187,-29,0,187,-29,0,-187,29,0,187,29,0],"indexes":[0,1,2,2,1,3],"uv":[0,58,374,58,0,0,374,0],"nuv":[0,0,1,0,0,1,1,1],"minPos":{"x":-187,"y":-29,"z":0},"maxPos":{"x":187,"y":29,"z":0}},"packable":true,"pixelsToUnit":100,"pivot":{"x":0.5,"y":0.5},"meshType":0}],[1],0,[0],[2],[17]],[[{"name":"Flag_of_Vietnam.svg","rect":{"x":0,"y":0,"width":225,"height":150},"offset":{"x":0,"y":0},"originalSize":{"width":225,"height":150},"rotated":false,"capInsets":[0,0,0,0],"vertices":{"rawPosition":[-112.5,-75,0,112.5,-75,0,-112.5,75,0,112.5,75,0],"indexes":[0,1,2,2,1,3],"uv":[0,150,225,150,0,0,225,0],"nuv":[0,0,1,0,0,1,1,1],"minPos":{"x":-112.5,"y":-75,"z":0},"maxPos":{"x":112.5,"y":75,"z":0}},"packable":true,"pixelsToUnit":100,"pivot":{"x":0.5,"y":0.5},"meshType":0}],[1],0,[0],[2],[18]],[[{"name":"love","rect":{"x":0,"y":3,"width":26,"height":23},"offset":{"x":0,"y":-1.5},"originalSize":{"width":26,"height":26},"rotated":false,"capInsets":[0,0,0,0],"vertices":{"rawPosition":[-13,-11.5,0,13,-11.5,0,-13,11.5,0,13,11.5,0],"indexes":[0,1,2,2,1,3],"uv":[0,23,26,23,0,0,26,0],"nuv":[0,0,1,0,0,0.8846153846153846,1,0.8846153846153846],"minPos":{"x":-13,"y":-11.5,"z":0},"maxPos":{"x":13,"y":11.5,"z":0}},"packable":true,"pixelsToUnit":100,"pivot":{"x":0.5,"y":0.5},"meshType":0}],[1],0,[0],[2],[19]],[[{"name":"default_scrollbar_vertical_bg","rect":{"x":0,"y":0,"width":15,"height":30},"offset":{"x":0,"y":0},"originalSize":{"width":15,"height":30},"rotated":false,"capInsets":[4,10,4,10],"vertices":{"rawPosition":[-7.5,-15,0,7.5,-15,0,-7.5,15,0,7.5,15,0],"indexes":[0,1,2,2,1,3],"uv":[0,30,15,30,0,0,15,0],"nuv":[0,0,1,0,0,1,1,1],"minPos":{"x":-7.5,"y":-15,"z":0},"maxPos":{"x":7.5,"y":15,"z":0}},"packable":true,"pixelsToUnit":100,"pivot":{"x":0.5,"y":0.5},"meshType":0}],[1],0,[0],[2],[20]]]]
